Metadata-Version: 2.4
Name: llama-index-vector-stores-vearch
Version: 0.4.1
Summary: llama-index vector_stores vearch integration
Author-email: Your Name <you@example.com>
License-Expression: MIT
License-File: LICENSE
Requires-Python: <4.0,>=3.9
Requires-Dist: llama-index-core<0.13,>=0.10.0
Requires-Dist: vearch-cluster<0.0.3,>=0.0.2
Requires-Dist: vearch<4,>=3.3.2
